opendigger_cli/__init__.py
opendigger_cli/main.py
opendigger_cli/test.py
opendigger_cli/test0.py
opendigger_cli/test2.py
opendigger_cli/test3.py
opendigger_cli/test4.py
opendigger_cli/functions/__init__.py
opendigger_cli/functions/base.py
opendigger_cli/functions/common.py
opendigger_cli/functions/metric_list.py
opendigger_cli/functions/query_month.py
opendigger_cli/functions/query_network.py
opendigger_cli-2.0.2.dist-info/METADATA
opendigger_cli-2.0.2.dist-info/WHEEL
opendigger_cli-2.0.2.dist-info/entry_points.txt
opendigger_cli-2.0.2.dist-info/top_level.txt
opendigger_cli-2.0.2.dist-info/RECORD
