Metadata-Version: 2.1
Name: opendigger-cli
Version: 2.0.2
Summary: opendigger-cli
Project-URL: Homepage, https://github.com/LinRS1999/opendigger-cli
Classifier: Programming Language :: Python :: 3
Classifier: License :: OSI Approved :: MIT License
Classifier: Operating System :: OS Independent
Requires-Python: >=3.8
